chaotic/__init__.py
chaotic/app.py
chaotic/log.py
chaotic/version.py
chaotic/cloud/__init__.py
chaotic/cloud/cloudscale_ch.py
chaotic/cloud/cloudstack.py
chaotic/cloud/digitalocean.py
chaotic/cloud/hcloud.py
chaotic/cloud/nomad.py
chaotic/cloud/proxmox.py
chaotic/cloud/vultr.py
chaotic_ngine-0.16.0.dist-info/licenses/LICENSE
chaotic_ngine-0.16.0.dist-info/METADATA
chaotic_ngine-0.16.0.dist-info/WHEEL
chaotic_ngine-0.16.0.dist-info/entry_points.txt
chaotic_ngine-0.16.0.dist-info/top_level.txt
chaotic_ngine-0.16.0.dist-info/RECORD
