Metadata-Version: 2.4
Name: chaotic-ngine
Version: 0.16.0
Summary: Chaos for Clouds.
Home-page: https://github.com/ngine-io/chaotic
Author: René Moser
Author-email: mail@renemoser.net
License: MIT
Classifier: Intended Audience :: Developers
Classifier: Intended Audience :: System Administrators
Classifier: Development Status :: 4 - Beta
Classifier: Programming Language :: Python :: 3
Classifier: License :: OSI Approved :: MIT License
Classifier: Operating System :: OS Independent
Classifier: Environment :: Web Environment
Requires-Python: >=3.10
License-File: LICENSE
Requires-Dist: certifi==2025.10.5
Requires-Dist: charset-normalizer==3.4.4
Requires-Dist: cloudscale-sdk==0.7.0
Requires-Dist: cs==3.4.0
Requires-Dist: hcloud==2.10.0
Requires-Dist: idna==3.11
Requires-Dist: jsonpickle==4.1.1
Requires-Dist: proxmoxer==2.2.0
Requires-Dist: python-dateutil==2.9.0.post0
Requires-Dist: python-digitalocean==1.17.0
Requires-Dist: python-dotenv==1.2.1
Requires-Dist: python-json-logger==4.0.0
Requires-Dist: pytz==2025.2
Requires-Dist: pyyaml==6.0.3
Requires-Dist: requests==2.32.5
Requires-Dist: schedule==1.2.2
Requires-Dist: six==1.17.0
Requires-Dist: truststore==0.10.4
Requires-Dist: urllib3==2.5.0
Requires-Dist: xdg==6.0.0
Dynamic: author
Dynamic: author-email
Dynamic: classifier
Dynamic: description
Dynamic: description-content-type
Dynamic: home-page
Dynamic: license
Dynamic: license-file
Dynamic: requires-dist
Dynamic: requires-python
Dynamic: summary
